dna_designer/__init__.py
dna_designer/barcode.py
dna_designer/basic_functions.py
dna_designer/codon.py
dna_designer/moclo.py
dna_designer/test.py
dna_designer/data/codon_usage.spsum
dna_designer/data/custom_table.spsum
dna_designer/data/frequency_example.csv
dna_designer/data/frequencycsv_to_spsum_generator.py
dna_designer-0.3.3.dist-info/METADATA
dna_designer-0.3.3.dist-info/WHEEL
dna_designer-0.3.3.dist-info/top_level.txt
dna_designer-0.3.3.dist-info/RECORD
