Metadata-Version: 2.1
Name: dna-designer
Version: 0.3.3
Summary: A package that assists in designing DNA
Home-page: UNKNOWN
Author: Keoni Gandall
Author-email: koeng101@gmail.com
License: UNKNOWN
Platform: UNKNOWN
Classifier: Programming Language :: Python :: 3
Classifier: License :: OSI Approved :: MIT License
Classifier: Operating System :: OS Independent
